pygments_style_tomorrow/__init__.py
pygments_style_tomorrow/tomorrow.py
pygments_style_tomorrow/tomorrownight.py
pygments_style_tomorrow/tomorrownightblue.py
pygments_style_tomorrow/tomorrownightbright.py
pygments_style_tomorrow/tomorrownighteighties.py
pygments_style_tomorrow-1.0.0.1.dist-info/METADATA
pygments_style_tomorrow-1.0.0.1.dist-info/WHEEL
pygments_style_tomorrow-1.0.0.1.dist-info/entry_points.txt
pygments_style_tomorrow-1.0.0.1.dist-info/top_level.txt
pygments_style_tomorrow-1.0.0.1.dist-info/RECORD
